 {"tutorials": [{"image": "https://jiahesa.github.io/ampack.github.io/webp/nuffge.jpg", "desc": {"cn": "【AM】最全面的手机摄像机教学！"}, "youtube": "https://b23.tv/XvPEkcj", "pos": 2, "title": {"cn": "【第一期——如何利用基础知识搭建一个小场景-哔哩哔哩】 "}}, {"image": "https://amfeng.cn/appdata/am/tutorial/sm_videothumb_get_started_2.webp", "desc": {"cn": "来自哔哩哔哩-冥晨mchleoxi"}, "youtube": "https://b23.tv/nNvQC0", "pos": 3, "title": {"cn": "3D教程-如何让3D运动更丝滑"}}, {"image": "https://amfeng.cn/appdata/am/tutorial/sm_videothumb_get_started_3.webp", "desc": {"cn": "来自哔哩哔哩-Nuffge泡芙"}, "youtube": "https://b23.tv/HmBOuu", "pos": 4, "title": {"cn": "IG风全基础教程"}}, {"image": "https://amfeng.cn/appdata/am/tutorial/sm_videothumb_get_started_4.webp", "desc": {"cn": "来自哔哩哔哩-7Enr_Ink"}, "youtube": "https://b23.tv/lr6OK4", "pos": 5, "title": {"cn": "用AM制作一个图案LOGO"}}, {"image": "https://amfeng.cn/appdata/am/tutorial/sm_videothumb_get_started_5.webp", "desc": {"cn": "来自哔哩哔哩-藤原AiR"}, "youtube": "https://b23.tv/z7S7sH", "pos": 6, "title": {"cn": "全网最细'锚点'教学"}}, {"image": "https://amfeng.cn/appdata/am/tutorial/sm_videothumb_get_started_6.webp", "desc": {"cn": "来自哔哩哔哩-Nuffge泡芙"}, "youtube": "https://b23.tv/sRAtvL", "pos": 7, "title": {"cn": "在AM上做出Twitch震动"}}, {"image": "https://amfeng.cn/appdata/am/tutorial/sm_videothumb_get_started_7.webp", "desc": {"cn": "来自哔哩哔哩-Bsoxxxxx"}, "youtube": "https://b23.tv/EPx3Kb", "pos": 8, "title": {"cn": "5分钟做一个长方形过渡转场"}}, {"image": "https://amfeng.cn/appdata/am/tutorial/sm_videothumb_get_started_8.webp", "desc": {"cn": "来自哔哩哔哩-7Enr_Ink"}, "youtube": "https://b23.tv/4c2kru", "pos": 9, "title": {"cn": "用AM做一个批爆的调色"}}, {"image": "https://amfeng.cn/appdata/am/tutorial/sm_videothumb_get_started_9.webp", "desc": {"cn": "来自哔哩哔哩--K-47_Official"}, "youtube": "https://b23.tv/EEBAxW", "pos": 10, "title": {"cn": "新手入门级手k和缩放教程"}}, {"image": "https://amfeng.cn/appdata/am/tutorial/sm_videothumb_get_started_10.webp", "desc": {"cn": "来自哔哩哔哩-祈奈亚子"}, "youtube": "https://b23.tv/4jBzZD", "pos": 11, "title": {"cn": "摄像机文字出场教程"}},}], "tips": [{"image": "", "desc": {"cn": ""}, "pos": 1, "title": {"cn": ""}}, {"image": "", "desc": {"cn": ""}, "pos": 2, "title": {"cn": ""}}, {"image": "", "desc": {"cn": ""}, "pos": 3, "title": {"cn": ""}}, {"image": "", "desc": {"cn": ""}, "pos": 4, "title": {"cn": ""}}, {"image": "", "desc": {"cn": ""}, "pos": 5, "title": {"cn": ""}}, {"image": "", "desc": {"cn": ""}, "pos": 8, "title": {"cn": ""}}, {"": "https://amfeng.cn/appdata/am/tutorial/more_bgthumb_7.webp", "desc": {"cn": ""}, "pos": 8, "title": {"cn": ""}}], "sampleProjects": [{"projectLink": "http://alight.link/p8X6jBDgo9SM8iB87", "image": "https://alightcreative.com/appdata/am/tutorial/thumb-small-1.jpg", "textColor": "#FFFFFF", "pos": 1, "title": {"cn": "旋转过渡"}}, {"projectLink": "http://alight.link/s8gq848Jd1h92okY8", "image": "https://alightcreative.com/appdata/am/tutorial/oozingtextmorph.jpg", "textColor": "#FFFFFF", "pos": 2, "title": {"cn": "渗出文本变形"}}, {"projectLink": "http://alight.link/UHgn9XyxoEDtEAoe6", "image": "https://alightcreative.com/appdata/am/tutorial/rgb-split.jpg", "textColor": "#FFFFFF", "pos": 3, "title": {"cn": "RGB分割"}}, {"projectLink": "http://alight.link/H4Riwnxx2ydcvtL56", "image": "https://alightcreative.com/appdata/am/tutorial/creepyscanlines.jpg", "textColor": "#FFFFFF", "pos": 4, "title": {"cn": "令人毛骨悚然的扫描线"}}]}